{
    "keep": {
        "days": true,
        "amount": 14
    },
    "auditLog": "logs\\server\\daily\\.66f9134d6120569f739e98c9ffd0130985b9b2a5-audit.json",
    "files": [
        {
            "date": 1723876167104,
            "name": "logs\\server\\daily\\2024-08-17.log",
            "hash": "0770704f078fccd4f91e5ab3ebb0c11b6f332815f547f43aba7f18cc696d64d9"
        },
        {
            "date": 1724046242535,
            "name": "logs\\server\\daily\\2024-08-19.log",
            "hash": "1c306004948e339518fa3fb484eff1d97160c75d0ffc0b37454d6d316baa6744"
        }
    ],
    "hashType": "sha256"
}